springs/__init__.py
springs/__main__.py
springs/commandline.py
springs/core.py
springs/field_utils.py
springs/field_utils.pyi
springs/flexyclasses.py
springs/initialize.py
springs/logging.py
springs/memoizer.py
springs/nicknames.py
springs/py.typed
springs/resolvers.py
springs/rich_utils.py
springs/shortcuts.py
springs/traversal.py
springs/types_utils.py
springs/utils.py
springs-1.13.0.dist-info/LICENSE
springs-1.13.0.dist-info/METADATA
springs-1.13.0.dist-info/WHEEL
springs-1.13.0.dist-info/top_level.txt
springs-1.13.0.dist-info/RECORD
