Metadata-Version: 2.1
Name: springs
Version: 1.13.0
Summary: A set of utilities to create and manage typed configuration files effectively, built on top of OmegaConf.
Author-email: Luca Soldaini <luca@soldaini.net>
License: Apache-2.0
Project-URL: Homepage, https://springs.soldaini.net
Project-URL: Source, https://github.com/soldni/Springs
Project-URL: Tracker, https://github.com/soldni/Springs/issues
Keywords: configuration,yaml,json,command line,cli,omegaconf,structured,config
Classifier: Development Status :: 4 - Beta
Classifier: License :: OSI Approved :: Apache Software License
Classifier: Operating System :: OS Independent
Classifier: Programming Language :: Python :: 3
Classifier: Topic :: Scientific/Engineering :: Artificial Intelligence
Classifier: Topic :: Software Development :: Libraries :: Python Modules
Classifier: Topic :: Utilities
Classifier: Typing :: Typed
Requires-Python: >=3.8
License-File: LICENSE
Requires-Dist: omegaconf (>=2.3.0)
Requires-Dist: types-pyyaml (>=6.0.0)
Requires-Dist: typing-extensions (>=4.2.0)
Requires-Dist: get-annotations (>=0.1.2)
Requires-Dist: platformdirs (>=2.5.0)
Requires-Dist: rich (>=11.0.0)
Requires-Dist: pathvalidate (>=2.5.0)
Provides-Extra: dev
Requires-Dist: black (>=22.6.0) ; extra == 'dev'
Requires-Dist: isort (>=5.10.1) ; extra == 'dev'
Requires-Dist: mypy (>=0.971) ; extra == 'dev'
Requires-Dist: pytest (>=5.2) ; extra == 'dev'
Requires-Dist: ipython (>=8.4.0) ; extra == 'dev'
Requires-Dist: autopep8 (>=1.7.0) ; extra == 'dev'
Requires-Dist: flake8 (>=5.0) ; extra == 'dev'
Requires-Dist: ipdb (>=0.13.0) ; extra == 'dev'
Requires-Dist: flake8-pyi (>=22.8.1) ; extra == 'dev'
Requires-Dist: Flake8-pyproject (>=1.1.0) ; extra == 'dev'
